smurphcast/__init__.py
smurphcast/_version.py
smurphcast/cli.py
smurphcast/pipeline.py
smurphcast/data/README.md
smurphcast/data/churn_example.csv
smurphcast/data/data_weekly.csv
smurphcast/evaluation/__init__.py
smurphcast/evaluation/backtest.py
smurphcast/evaluation/metrics.py
smurphcast/explain/explainer.py
smurphcast/features/__init__.py
smurphcast/features/lag_feats.py
smurphcast/features/time_feats.py
smurphcast/losses/__init__.py
smurphcast/losses/bounded.py
smurphcast/models/__init__.py
smurphcast/models/_base.py
smurphcast/models/additive.py
smurphcast/models/auto_selector.py
smurphcast/models/beta_rnn.py
smurphcast/models/gbm.py
smurphcast/models/hybrid_esrnn.py
smurphcast/models/quantile_gbm.py
smurphcast/preprocessing/__init__.py
smurphcast/preprocessing/outlier.py
smurphcast/preprocessing/transform.py
smurphcast/preprocessing/validator.py
smurphcast-1.0.7.dist-info/METADATA
smurphcast-1.0.7.dist-info/WHEEL
smurphcast-1.0.7.dist-info/entry_points.txt
smurphcast-1.0.7.dist-info/licenses/LICENSE
smurphcast-1.0.7.dist-info/RECORD
