Metadata-Version: 2.4
Name: smurphcast
Version: 1.0.7
Summary: Boundary-aware, modular forecasting for percentage KPIs.
Project-URL: Homepage, https://github.com/Halsted312/smurphcast
Project-URL: Docs, https://Halsted312.github.io/SmurphCast
Author-email: Stephen Murphy <stephenjmurph@gmail.com>
License: MIT
License-File: LICENSE
Requires-Python: >=3.9
Requires-Dist: joblib>=1.4
Requires-Dist: lightgbm>=4.3
Requires-Dist: matplotlib>=3.8
Requires-Dist: numpy>=1.24
Requires-Dist: pandas>=2.1
Requires-Dist: scikit-learn>=1.4
Requires-Dist: scipy>=1.12
Requires-Dist: statsmodels>=0.14
Requires-Dist: torch>=2.3
Requires-Dist: tqdm>=4.66
Requires-Dist: typer>=0.12
Provides-Extra: dev
Requires-Dist: black; extra == 'dev'
Requires-Dist: pre-commit; extra == 'dev'
Requires-Dist: pytest; extra == 'dev'
Requires-Dist: ruff; extra == 'dev'
Provides-Extra: docs
Requires-Dist: jupyter; extra == 'docs'
Requires-Dist: mkdocs-material; extra == 'docs'
Requires-Dist: mkdocstrings[python]; extra == 'docs'
